metaplanet_room_chat/__init__.py
metaplanet_room_chat/client.py
metaplanet_room_chat/config.py
metaplanet_room_chat/handlers.py
metaplanet_room_chat-0.0.3.dist-info/METADATA
metaplanet_room_chat-0.0.3.dist-info/WHEEL
metaplanet_room_chat-0.0.3.dist-info/top_level.txt
metaplanet_room_chat-0.0.3.dist-info/RECORD
